LICENSE
stail/__init__.py
stail-0.2.2.dist-info/entry_points.txt
stail-0.2.2.dist-info/LICENSE
stail-0.2.2.dist-info/WHEEL
stail-0.2.2.dist-info/METADATA
stail-0.2.2.dist-info/RECORD
