Metadata-Version: 2.1
Name: stail
Version: 0.2.2
Summary: CLI Tool to run and tail a step function synchronously.
Home-page: https://github.com/imankamyabi/stail
License: MIT
Keywords: step-function,aws,cli,tail,state-machine
Author: Iman Kamyabi
Author-email: contact@imankamyabi.com
Requires-Python: >=3.7,<4.0
Classifier: Environment :: Console
Classifier: License :: OSI Approved :: MIT License
Classifier: Operating System :: OS Independent
Classifier: Programming Language :: Python :: 3
Classifier: Programming Language :: Python :: 3.7
Classifier: Programming Language :: Python :: 3.8
Classifier: Topic :: Software Development :: Libraries :: Python Modules
Requires-Dist: boto3 (>=1.11.14,<2.0.0)
Requires-Dist: click (>=7.0,<8.0)
Requires-Dist: colorama (>=0.4.3,<0.5.0)
Requires-Dist: pyfiglet (>=0.8.post1,<0.9)
Project-URL: Repository, https://github.com/imankamyabi/stail
